LICENSE
README.md
setup.py
d_igloo.egg-info/PKG-INFO
d_igloo.egg-info/SOURCES.txt
d_igloo.egg-info/dependency_links.txt
d_igloo.egg-info/entry_points.txt
d_igloo.egg-info/requires.txt
d_igloo.egg-info/top_level.txt
igloo/S3Glacier.py
igloo/__init__.py
igloo/igloo_cli.py