Metadata-Version: 2.1
Name: d-igloo
Version: 1.0
Summary: A command line tool to archive and retrieve project's data to and from Amazon AWS S3 Glacier for D-ICE Engineering needs.
Home-page: https://d-ice.gitlab.host/common/igloo
Author: Francois Rongere
Author-email: francois.rongere@dice-engineering.com
Classifier: License :: OSI Approved :: MIT License
Classifier: Operating System :: OS Independent
Classifier: Programming Language :: Python
Classifier: Programming Language :: Python :: 3
Classifier: Natural Language :: English
License-File: LICENSE
